{"makers":[{"name":"doubleSum","classPath":"com.yahoo.bard.webservice.data.config.metric.makers.DoubleSumMaker"}],"metrics":[{"apiName":"absoluteHumidity","longName":"absoluteHumidity","maker":"doubleSum","dependencyMetricNames":["absoluteHumidity"]},{"apiName":"NO2","longName":"NO2","maker":"doubleSum","dependencyMetricNames":["NO2"]},{"apiName":"relativeHumidity","longName":"relativeHumidity","maker":"doubleSum","dependencyMetricNames":["relativeHumidity"]},{"apiName":"deleted","longName":"deleted","maker":"doubleSum","dependencyMetricNames":["deleted"]},{"apiName":"count","longName":"count","maker":"doubleSum","dependencyMetricNames":["count"]},{"apiName":"O3","longName":"O3","maker":"doubleSum","dependencyMetricNames":["O3"]},{"apiName":"added","longName":"added","maker":"doubleSum","dependencyMetricNames":["added"]},{"apiName":"user_unique","longName":"user_unique","maker":"doubleSum","dependencyMetricNames":["user_unique"]},{"apiName":"Temp","longName":"Temp","maker":"doubleSum","dependencyMetricNames":["Temp"]},{"apiName":"NMHC","longName":"NMHC","maker":"doubleSum","dependencyMetricNames":["NMHC"]},{"apiName":"count","longName":"count","maker":"doubleSum","dependencyMetricNames":["count"]},{"apiName":"NOx","longName":"NOx","maker":"doubleSum","dependencyMetricNames":["NOx"]},{"apiName":"CO","longName":"CO","maker":"doubleSum","dependencyMetricNames":["CO"]},{"apiName":"C6H6","longName":"C6H6","maker":"doubleSum","dependencyMetricNames":["C6H6"]},{"apiName":"delta","longName":"delta","maker":"doubleSum","dependencyMetricNames":["delta"]}]}